MANIFEST.in
README.rst
setup.py
django_slimmer.egg-info/PKG-INFO
django_slimmer.egg-info/SOURCES.txt
django_slimmer.egg-info/dependency_links.txt
django_slimmer.egg-info/not-zip-safe
django_slimmer.egg-info/requires.txt
django_slimmer.egg-info/top_level.txt
slimmer/__init__.py
slimmer/decorator.py
slimmer/middleware.py
slimmer/slimmer.py