Metadata-Version: 1.0
Name: django-slimmer
Version: 0.0.2
Summary: Html compression as middleware and view decorators
Home-page: http://github.com/hbussell/django-slimmer
Author: Harley Bussell
Author-email: modmac@gmail.com
License: MIT
Keywords: django html compressor
Platform: UNKNOWN
Classifier: Programming Language :: Python
Classifier: Development Status :: 4 - Beta
Classifier: Intended Audience :: Developers
Classifier: Framework :: Django
